README.md
setup.py
YoBit/__init__.py
YoBit/__version__.py
YoBit/build.py
YoBit.egg-info/PKG-INFO
YoBit.egg-info/SOURCES.txt
YoBit.egg-info/dependency_links.txt
YoBit.egg-info/entry_points.txt
YoBit.egg-info/top_level.txt