Metadata-Version: 1.1
Name: YoBit
Version: 0.0.1.1
Summary: Python wrapper for YoBit API
Home-page: https://github.com/Mambix/yobit
Author: Mambix Ltd.
Author-email: ledi.mambix@gmail.com
License: MIT
Platform: UNKNOWN
Classifier: Programming Language :: Python
Classifier: Programming Language :: Python :: 2
Classifier: Programming Language :: Python :: 3
